zenodo_uploader/__init__.py
zenodo_uploader/cli.py
zenodo_uploader-0.1.3.dist-info/METADATA
zenodo_uploader-0.1.3.dist-info/WHEEL
zenodo_uploader-0.1.3.dist-info/entry_points.txt
zenodo_uploader-0.1.3.dist-info/top_level.txt
zenodo_uploader-0.1.3.dist-info/RECORD
