Metadata-Version: 2.4
Name: zenodo-uploader
Version: 0.1.3
Summary: A command-line tool and library to upload files to Zenodo.
Author-email: Lei Wang <wanglei94@hust.edu.cn>
License: MIT License
Project-URL: Homepage, https://github.com/wangleiofficial/zenodo-uploader
Project-URL: Issues, https://github.com/wangleiofficial/zenodo-uploader/issues
Classifier: Programming Language :: Python :: 3
Classifier: License :: OSI Approved :: MIT License
Classifier: Operating System :: OS Independent
Classifier: Topic :: Scientific/Engineering
Classifier: Topic :: System :: Archiving
Requires-Python: >=3.7
Requires-Dist: requests
Requires-Dist: toml
Requires-Dist: tqdm
